{
  "date": "2026-06-03",
  "model": "v5-lgb-two-model",
  "model_version": "v5",
  "calibration_k": 0.5,
  "model_mean": 0.46838190264689916,
  "regime_rates": {
    "rolling_30d_yrfi": 0.4975247524752475,
    "rolling_30d_top1": 0.25495049504950495,
    "rolling_30d_bot1": 0.29455445544554454,
    "as_of": "2026-05-23",
    "n_games_in_window": 404
  },
  "health": {
    "kelly_scale": 0.5,
    "paused": false,
    "reason": "drawdown_halve: -50.7% from peak",
    "max_drawdown_pct": 50.69,
    "avg_clv_14d": null,
    "n_clv_samples": 0
  },
  "effective_kelly_fraction": 0.125,
  "bankroll": 1000.0,
  "bankroll_current": 567.08,
  "generated_at": "2026-06-03T17:56:20.232179+00:00",
  "games": [
    {
      "game_pk": 823130,
      "date": "2026-06-03",
      "away_team": "NYM",
      "home_team": "SEA",
      "away_starter": "Freddy Peralta",
      "home_starter": "George Kirby",
      "umpire": "Adam Beck",
      "p_top": 0.2446,
      "p_bot": 0.272,
      "p_raw": 0.4501,
      "p_cal": 0.4388,
      "mkt_y_fair": 0.448,
      "mkt_n_fair": 0.552,
      "agreement": "NRFI",
      "bet_side": "NRFI",
      "bet_edge": 0.0092,
      "bet_kelly": 0.0,
      "bet_odds": -142.0,
      "open_odds": -145.0,
      "bet_dec": 1.704,
      "passes_filter": false,
      "skip_reason": "kelly < 1%",
      "stake": 0.0,
      "n_books": 3,
      "best_odds": -135,
      "best_book": "williamhill_us",
      "best_dec": 1.741,
      "mkt_y_impl": 0.4762,
      "mkt_n_impl": 0.5868,
      "forecast_weather": null,
      "pick_factors": {
        "away_fi_runs_per_start": 0.38,
        "home_fi_runs_per_start": 0.4,
        "away_fi_k_rate": 0.306,
        "home_fi_k_rate": 0.271,
        "away_recent_fi_runs": 0.0,
        "home_recent_fi_runs": 0.0,
        "away_avg_velo": 94.5,
        "home_avg_velo": 96.2,
        "away_platoon_k_rate": 0.281,
        "home_platoon_k_rate": 0.237,
        "away_lineup_weighted_score": 1.411,
        "home_lineup_weighted_score": 1.448,
        "away_platoon_lineup_woba": 0.327,
        "home_platoon_lineup_woba": 0.335,
        "umpire_strike_rate": 0.331,
        "park_factor_runs": 94.0,
        "elevation_ft": 15
      }
    }
  ],
  "bets": [],
  "summary": {
    "total_games": 1,
    "total_bets": 0,
    "yrfi_bets": 0,
    "nrfi_bets": 0,
    "total_exposure": 0
  }
}