{
  "date": "2026-06-15",
  "model": "v5-lgb-two-model",
  "model_version": "v5",
  "calibration_k": 0.5,
  "model_mean": 0.4725473127569084,
  "regime_rates": {
    "rolling_30d_yrfi": 0.5187032418952618,
    "rolling_30d_top1": 0.2718204488778055,
    "rolling_30d_bot1": 0.2967581047381546,
    "as_of": "2026-06-06",
    "n_games_in_window": 401
  },
  "health": {
    "kelly_scale": 0.5,
    "paused": false,
    "reason": "drawdown_halve: -50.7% from peak",
    "max_drawdown_pct": 50.69,
    "avg_clv_14d": null,
    "n_clv_samples": 0
  },
  "effective_kelly_fraction": 0.125,
  "bankroll": 1000.0,
  "bankroll_current": 638.36,
  "generated_at": "2026-06-16T00:15:16.433375+00:00",
  "games": [
    {
      "game_pk": 823452,
      "date": "2026-06-15",
      "away_team": "MIA",
      "home_team": "PHI",
      "away_starter": "Ryan Gusto",
      "home_starter": "Zack Wheeler",
      "umpire": "Tripp Gibson",
      "p_top": 0.1814,
      "p_bot": 0.4467,
      "p_raw": 0.5471,
      "p_cal": 0.5185,
      "mkt_y_fair": 0.4812,
      "mkt_n_fair": 0.5188,
      "agreement": "MIXED",
      "bet_side": "YRFI",
      "bet_edge": 0.0373,
      "bet_kelly": 0.0022,
      "bet_odds": -104.0,
      "open_odds": -102.0,
      "bet_dec": 1.962,
      "passes_filter": false,
      "skip_reason": "mixed agreement",
      "stake": 0.0,
      "n_books": 3,
      "best_odds": -102,
      "best_book": "betmgm",
      "best_dec": 1.98,
      "mkt_y_impl": 0.5098,
      "mkt_n_impl": 0.5495,
      "forecast_weather": null,
      "pick_factors": {
        "away_fi_runs_per_start": 0.65,
        "home_fi_runs_per_start": 0.23,
        "away_fi_k_rate": 0.24,
        "home_fi_k_rate": 0.301,
        "away_recent_fi_runs": 1.33,
        "home_recent_fi_runs": 0.33,
        "away_avg_velo": 94.0,
        "home_avg_velo": 95.4,
        "away_platoon_k_rate": 0.216,
        "home_platoon_k_rate": 0.292,
        "away_lineup_weighted_score": 1.383,
        "home_lineup_weighted_score": 1.561,
        "away_platoon_lineup_woba": 0.335,
        "home_platoon_lineup_woba": 0.355,
        "umpire_strike_rate": 0.33,
        "park_factor_runs": 106.0,
        "elevation_ft": 20
      }
    },
    {
      "game_pk": 822724,
      "date": "2026-06-15",
      "away_team": "KCR",
      "home_team": "WSN",
      "away_starter": "Mitch Spence",
      "home_starter": "Andrew Alvarez",
      "umpire": "Chad Whitson",
      "p_top": 0.2178,
      "p_bot": 0.4131,
      "p_raw": 0.5409,
      "p_cal": 0.5714,
      "mkt_y_fair": 0.5372,
      "mkt_n_fair": 0.4628,
      "agreement": "MIXED",
      "bet_side": "YRFI",
      "bet_edge": 0.0342,
      "bet_kelly": 0.0007,
      "bet_odds": -132.0,
      "open_odds": -125.0,
      "bet_dec": 1.758,
      "passes_filter": false,
      "skip_reason": "mixed agreement",
      "stake": 0.0,
      "n_books": 3,
      "best_odds": -125,
      "best_book": "betmgm",
      "best_dec": 1.8,
      "mkt_y_impl": 0.569,
      "mkt_n_impl": 0.4902,
      "forecast_weather": null,
      "pick_factors": {
        "away_fi_runs_per_start": 0.53,
        "home_fi_runs_per_start": 0.2,
        "away_fi_k_rate": 0.232,
        "home_fi_k_rate": 0.188,
        "away_recent_fi_runs": 2.0,
        "home_recent_fi_runs": 0.33,
        "away_avg_velo": 92.0,
        "home_avg_velo": 91.5,
        "away_platoon_k_rate": 0.2,
        "home_platoon_k_rate": 0.22,
        "away_lineup_weighted_score": 1.343,
        "home_lineup_weighted_score": 1.352,
        "away_platoon_lineup_woba": 0.336,
        "home_platoon_lineup_woba": 0.324,
        "umpire_strike_rate": 0.33,
        "park_factor_runs": 100.0,
        "elevation_ft": 25
      }
    },
    {
      "game_pk": 824505,
      "date": "2026-06-15",
      "away_team": "NYM",
      "home_team": "CIN",
      "away_starter": "Tobias Myers",
      "home_starter": "Chase Burns",
      "umpire": "Mark Wegner",
      "p_top": 0.3419,
      "p_bot": 0.4266,
      "p_raw": 0.6227,
      "p_cal": 0.5563,
      "mkt_y_fair": 0.4812,
      "mkt_n_fair": 0.5188,
      "agreement": "YRFI",
      "bet_side": "YRFI",
      "bet_edge": 0.0751,
      "bet_kelly": 0.0119,
      "bet_odds": -104.0,
      "open_odds": 100.0,
      "bet_dec": 1.962,
      "passes_filter": true,
      "skip_reason": "",
      "stake": 7.57,
      "n_books": 3,
      "best_odds": 100,
      "best_book": "betmgm",
      "best_dec": 2.0,
      "mkt_y_impl": 0.5098,
      "mkt_n_impl": 0.5495,
      "forecast_weather": null,
      "pick_factors": {
        "away_fi_runs_per_start": 0.38,
        "home_fi_runs_per_start": 0.44,
        "away_fi_k_rate": 0.244,
        "home_fi_k_rate": 0.429,
        "away_recent_fi_runs": 0.33,
        "home_recent_fi_runs": 0.0,
        "away_avg_velo": 93.0,
        "home_avg_velo": 98.4,
        "away_platoon_k_rate": 0.213,
        "home_platoon_k_rate": 0.308,
        "away_lineup_weighted_score": 1.421,
        "home_lineup_weighted_score": 1.386,
        "away_platoon_lineup_woba": 0.328,
        "home_platoon_lineup_woba": 0.323,
        "umpire_strike_rate": 0.314,
        "park_factor_runs": 108.0,
        "elevation_ft": 490
      }
    },
    {
      "game_pk": 823046,
      "date": "2026-06-15",
      "away_team": "SDP",
      "home_team": "STL",
      "away_starter": "Wandy Peralta",
      "home_starter": "Dustin May",
      "umpire": "Laz Diaz",
      "p_top": 0.1917,
      "p_bot": 0.3044,
      "p_raw": 0.4378,
      "p_cal": 0.4868,
      "mkt_y_fair": 0.5042,
      "mkt_n_fair": 0.4958,
      "agreement": "MIXED",
      "bet_side": "NRFI",
      "bet_edge": 0.0174,
      "bet_kelly": 0.0,
      "bet_odds": -111.0,
      "open_odds": -111.0,
      "bet_dec": 1.901,
      "passes_filter": false,
      "skip_reason": "mixed agreement",
      "stake": 0.0,
      "n_books": 3,
      "best_odds": -110,
      "best_book": "betmgm",
      "best_dec": 1.909,
      "mkt_y_impl": 0.5349,
      "mkt_n_impl": 0.5261,
      "forecast_weather": null,
      "pick_factors": {
        "away_fi_runs_per_start": 0.5,
        "home_fi_runs_per_start": 0.62,
        "away_fi_k_rate": 0.19,
        "home_fi_k_rate": 0.215,
        "away_recent_fi_runs": 0.0,
        "home_recent_fi_runs": 0.33,
        "away_avg_velo": 95.4,
        "home_avg_velo": 95.4,
        "away_platoon_k_rate": 0.194,
        "home_platoon_k_rate": 0.197,
        "away_lineup_weighted_score": 1.411,
        "home_lineup_weighted_score": 1.476,
        "away_platoon_lineup_woba": 0.335,
        "home_platoon_lineup_woba": 0.315,
        "umpire_strike_rate": 0.326,
        "park_factor_runs": 97.0,
        "elevation_ft": 455
      }
    },
    {
      "game_pk": 822887,
      "date": "2026-06-15",
      "away_team": "MIN",
      "home_team": "TEX",
      "away_starter": "Mike Paredes",
      "home_starter": "MacKenzie Gore",
      "umpire": "Derek Thomas",
      "p_top": 0.295,
      "p_bot": 0.2612,
      "p_raw": 0.4791,
      "p_cal": 0.4845,
      "mkt_y_fair": 0.4812,
      "mkt_n_fair": 0.5188,
      "agreement": "MIXED",
      "bet_side": "YRFI",
      "bet_edge": 0.0033,
      "bet_kelly": 0.0,
      "bet_odds": -104.0,
      "open_odds": -104.0,
      "bet_dec": 1.962,
      "passes_filter": false,
      "skip_reason": "mixed agreement",
      "stake": 0.0,
      "n_books": 3,
      "best_odds": 100,
      "best_book": "williamhill_us",
      "best_dec": 2.0,
      "mkt_y_impl": 0.5098,
      "mkt_n_impl": 0.5495,
      "forecast_weather": null,
      "pick_factors": {
        "away_fi_runs_per_start": 0.5,
        "home_fi_runs_per_start": 0.49,
        "away_fi_k_rate": 0.225,
        "home_fi_k_rate": 0.274,
        "away_recent_fi_runs": 0.5,
        "home_recent_fi_runs": 0.33,
        "away_avg_velo": 93.0,
        "home_avg_velo": 95.5,
        "away_platoon_k_rate": 0.225,
        "home_platoon_k_rate": 0.256,
        "away_lineup_weighted_score": 1.389,
        "home_lineup_weighted_score": 1.409,
        "away_platoon_lineup_woba": 0.317,
        "home_platoon_lineup_woba": 0.327,
        "umpire_strike_rate": 0.315,
        "park_factor_runs": 101.0,
        "elevation_ft": 545
      }
    },
    {
      "game_pk": 824666,
      "date": "2026-06-15",
      "away_team": "COL",
      "home_team": "CHC",
      "away_starter": "Michael Lorenzen",
      "home_starter": "Shota Imanaga",
      "umpire": "James Hoye",
      "p_top": 0.1713,
      "p_bot": 0.308,
      "p_raw": 0.4265,
      "p_cal": 0.5076,
      "mkt_y_fair": 0.5306,
      "mkt_n_fair": 0.4694,
      "agreement": "MIXED",
      "bet_side": "NRFI",
      "bet_edge": 0.023,
      "bet_kelly": 0.0,
      "bet_odds": 100.0,
      "open_odds": 100.0,
      "bet_dec": 2.0,
      "passes_filter": false,
      "skip_reason": "mixed agreement",
      "stake": 0.0,
      "n_books": 3,
      "best_odds": 110,
      "best_book": "fanduel",
      "best_dec": 2.1,
      "mkt_y_impl": 0.5652,
      "mkt_n_impl": 0.5,
      "forecast_weather": null,
      "pick_factors": {
        "away_fi_runs_per_start": 0.4,
        "home_fi_runs_per_start": 0.57,
        "away_fi_k_rate": 0.24,
        "home_fi_k_rate": 0.271,
        "away_recent_fi_runs": 0.67,
        "home_recent_fi_runs": 1.0,
        "away_avg_velo": 93.8,
        "home_avg_velo": 91.2,
        "away_platoon_k_rate": 0.182,
        "home_platoon_k_rate": 0.239,
        "away_lineup_weighted_score": 1.357,
        "home_lineup_weighted_score": 1.439,
        "away_platoon_lineup_woba": 0.286,
        "home_platoon_lineup_woba": 0.346,
        "umpire_strike_rate": 0.322,
        "park_factor_runs": 103.0,
        "elevation_ft": 600
      }
    },
    {
      "game_pk": 824181,
      "date": "2026-06-15",
      "away_team": "DET",
      "home_team": "HOU",
      "away_starter": "Drew Anderson",
      "home_starter": "Kai-Wei Teng",
      "umpire": "Paul Clemons",
      "p_top": 0.2248,
      "p_bot": 0.2781,
      "p_raw": 0.4404,
      "p_cal": 0.4921,
      "mkt_y_fair": 0.5082,
      "mkt_n_fair": 0.4918,
      "agreement": "NRFI",
      "bet_side": "NRFI",
      "bet_edge": 0.0161,
      "bet_kelly": 0.0,
      "bet_odds": -110.0,
      "open_odds": -110.0,
      "bet_dec": 1.909,
      "passes_filter": false,
      "skip_reason": "kelly < 1%",
      "stake": 0.0,
      "n_books": 3,
      "best_odds": 102,
      "best_book": "fanduel",
      "best_dec": 2.02,
      "mkt_y_impl": 0.5413,
      "mkt_n_impl": 0.5238,
      "forecast_weather": null,
      "pick_factors": {
        "away_fi_runs_per_start": 0.5,
        "home_fi_runs_per_start": 1.0,
        "away_fi_k_rate": 0.282,
        "home_fi_k_rate": 0.262,
        "away_recent_fi_runs": 0.5,
        "home_recent_fi_runs": 1.33,
        "away_avg_velo": 94.9,
        "home_avg_velo": 93.5,
        "away_platoon_k_rate": 0.288,
        "home_platoon_k_rate": 0.225,
        "away_lineup_weighted_score": 1.544,
        "home_lineup_weighted_score": 1.54,
        "away_platoon_lineup_woba": 0.357,
        "home_platoon_lineup_woba": 0.345,
        "umpire_strike_rate": 0.327,
        "park_factor_runs": 100.0,
        "elevation_ft": 0
      }
    },
    {
      "game_pk": 825071,
      "date": "2026-06-15",
      "away_team": "LAA",
      "home_team": "ARI",
      "away_starter": "Walbert Ure\u00f1a",
      "home_starter": "Ryne Nelson",
      "umpire": "Vic Carapazza",
      "p_top": 0.2032,
      "p_bot": 0.3852,
      "p_raw": 0.5102,
      "p_cal": 0.5391,
      "mkt_y_fair": 0.5203,
      "mkt_n_fair": 0.4797,
      "agreement": "MIXED",
      "bet_side": "YRFI",
      "bet_edge": 0.0188,
      "bet_kelly": 0.0,
      "bet_odds": -125.0,
      "open_odds": -115.0,
      "bet_dec": 1.8,
      "passes_filter": false,
      "skip_reason": "mixed agreement",
      "stake": 0.0,
      "n_books": 3,
      "best_odds": -115,
      "best_book": "betmgm",
      "best_dec": 1.87,
      "mkt_y_impl": 0.5556,
      "mkt_n_impl": 0.5122,
      "forecast_weather": null,
      "pick_factors": {
        "away_fi_runs_per_start": 0.0,
        "home_fi_runs_per_start": 0.41,
        "away_fi_k_rate": 0.267,
        "home_fi_k_rate": 0.234,
        "away_recent_fi_runs": 0.0,
        "home_recent_fi_runs": 0.0,
        "away_avg_velo": 97.9,
        "home_avg_velo": 95.3,
        "away_platoon_k_rate": 0.207,
        "home_platoon_k_rate": 0.201,
        "away_lineup_weighted_score": 1.359,
        "home_lineup_weighted_score": 1.514,
        "away_platoon_lineup_woba": 0.311,
        "home_platoon_lineup_woba": 0.342,
        "umpire_strike_rate": 0.335,
        "park_factor_runs": 106.0,
        "elevation_ft": 1100
      }
    },
    {
      "game_pk": 824993,
      "date": "2026-06-15",
      "away_team": "PIT",
      "home_team": "OAK",
      "away_starter": "Jared Jones",
      "home_starter": "J.T. Ginn",
      "umpire": "Charlie Ramos",
      "p_top": 0.1638,
      "p_bot": 0.2751,
      "p_raw": 0.3939,
      "p_cal": 0.5296,
      "mkt_y_fair": 0.569,
      "mkt_n_fair": 0.431,
      "agreement": "NRFI",
      "bet_side": "NRFI",
      "bet_edge": 0.0393,
      "bet_kelly": 0.0036,
      "bet_odds": 120.0,
      "open_odds": 120.0,
      "bet_dec": 2.2,
      "passes_filter": false,
      "skip_reason": "kelly < 1%",
      "stake": 0.0,
      "n_books": 3,
      "best_odds": 142,
      "best_book": "fanduel",
      "best_dec": 2.42,
      "mkt_y_impl": 0.6,
      "mkt_n_impl": 0.4545,
      "forecast_weather": null,
      "pick_factors": {
        "away_fi_runs_per_start": 0.41,
        "home_fi_runs_per_start": 0.64,
        "away_fi_k_rate": 0.292,
        "home_fi_k_rate": 0.26,
        "away_recent_fi_runs": 0.0,
        "home_recent_fi_runs": 0.0,
        "away_avg_velo": 97.3,
        "home_avg_velo": 93.5,
        "away_platoon_k_rate": 0.265,
        "home_platoon_k_rate": 0.219,
        "away_lineup_weighted_score": 1.446,
        "home_lineup_weighted_score": 1.533,
        "away_platoon_lineup_woba": 0.343,
        "home_platoon_lineup_woba": 0.366,
        "umpire_strike_rate": 0.322,
        "park_factor_runs": 100.0,
        "elevation_ft": 0
      }
    },
    {
      "game_pk": 823938,
      "date": "2026-06-15",
      "away_team": "TBR",
      "home_team": "LAD",
      "away_starter": "Nick Martinez",
      "home_starter": "Eric Lauer",
      "umpire": "Dan Merzel",
      "p_top": 0.3354,
      "p_bot": 0.3475,
      "p_raw": 0.5663,
      "p_cal": 0.5775,
      "mkt_y_fair": 0.5306,
      "mkt_n_fair": 0.4694,
      "agreement": "YRFI",
      "bet_side": "YRFI",
      "bet_edge": 0.0469,
      "bet_kelly": 0.0035,
      "bet_odds": -130.0,
      "open_odds": -125.0,
      "bet_dec": 1.769,
      "passes_filter": false,
      "skip_reason": "kelly < 1%",
      "stake": 0.0,
      "n_books": 3,
      "best_odds": -130,
      "best_book": "betmgm",
      "best_dec": 1.769,
      "mkt_y_impl": 0.5652,
      "mkt_n_impl": 0.5,
      "forecast_weather": null,
      "pick_factors": {
        "away_fi_runs_per_start": 0.23,
        "home_fi_runs_per_start": 0.76,
        "away_fi_k_rate": 0.223,
        "home_fi_k_rate": 0.216,
        "away_recent_fi_runs": 0.0,
        "home_recent_fi_runs": 1.33,
        "away_avg_velo": 92.6,
        "home_avg_velo": 91.3,
        "away_platoon_k_rate": 0.197,
        "home_platoon_k_rate": 0.215,
        "away_lineup_weighted_score": 1.453,
        "home_lineup_weighted_score": 1.665,
        "away_platoon_lineup_woba": 0.34,
        "home_platoon_lineup_woba": 0.377,
        "umpire_strike_rate": 0.329,
        "park_factor_runs": 100.0,
        "elevation_ft": 0
      }
    }
  ],
  "bets": [
    {
      "game_pk": 824505,
      "date": "2026-06-15",
      "away_team": "NYM",
      "home_team": "CIN",
      "away_starter": "Tobias Myers",
      "home_starter": "Chase Burns",
      "umpire": "Mark Wegner",
      "p_top": 0.3419,
      "p_bot": 0.4266,
      "p_raw": 0.6227,
      "p_cal": 0.5563,
      "mkt_y_fair": 0.4812,
      "mkt_n_fair": 0.5188,
      "agreement": "YRFI",
      "bet_side": "YRFI",
      "bet_edge": 0.0751,
      "bet_kelly": 0.0119,
      "bet_odds": -104.0,
      "open_odds": 100.0,
      "bet_dec": 1.962,
      "passes_filter": true,
      "skip_reason": "",
      "stake": 7.57,
      "n_books": 3,
      "best_odds": 100,
      "best_book": "betmgm",
      "best_dec": 2.0,
      "mkt_y_impl": 0.5098,
      "mkt_n_impl": 0.5495,
      "forecast_weather": null,
      "pick_factors": {
        "away_fi_runs_per_start": 0.38,
        "home_fi_runs_per_start": 0.44,
        "away_fi_k_rate": 0.244,
        "home_fi_k_rate": 0.429,
        "away_recent_fi_runs": 0.33,
        "home_recent_fi_runs": 0.0,
        "away_avg_velo": 93.0,
        "home_avg_velo": 98.4,
        "away_platoon_k_rate": 0.213,
        "home_platoon_k_rate": 0.308,
        "away_lineup_weighted_score": 1.421,
        "home_lineup_weighted_score": 1.386,
        "away_platoon_lineup_woba": 0.328,
        "home_platoon_lineup_woba": 0.323,
        "umpire_strike_rate": 0.314,
        "park_factor_runs": 108.0,
        "elevation_ft": 490
      }
    }
  ],
  "summary": {
    "total_games": 10,
    "total_bets": 1,
    "yrfi_bets": 1,
    "nrfi_bets": 0,
    "total_exposure": 7.57
  }
}